llvm_diagnostics/__init__.py
llvm_diagnostics/formatters.py
llvm_diagnostics/messages.py
llvm_diagnostics/parser.py
llvm_diagnostics/utils.py
llvm_diagnostics-3.0.1.dist-info/LICENSE.md
llvm_diagnostics-3.0.1.dist-info/METADATA
llvm_diagnostics-3.0.1.dist-info/WHEEL
llvm_diagnostics-3.0.1.dist-info/top_level.txt
llvm_diagnostics-3.0.1.dist-info/zip-safe
llvm_diagnostics-3.0.1.dist-info/RECORD
