Metadata-Version: 2.1
Name: llvm-diagnostics
Version: 3.0.1
Summary: Python module for creating diagnostics using the LLVM diagnostics specification
Home-page: https://github.com/tomtom-international/llvm-diagnostics
Author: Kevin de Jong
Author-email: KevinDeJong@tomtom.com
License: Apache License 2.0
Download-URL: https://github.com/tomtom-international/llvm-diagnostics
Keywords: diagnostics logger logging llvm
Platform: UNKNOWN
Classifier: License :: OSI Approved :: Apache Software License
Requires-Python: >=3.7
Requires-Dist: typing-extensions <5,>=4.2.0
